django_rest_hooks-1.5.0.dist-info/DESCRIPTION.rst
django_rest_hooks-1.5.0.dist-info/METADATA
django_rest_hooks-1.5.0.dist-info/RECORD
django_rest_hooks-1.5.0.dist-info/WHEEL
django_rest_hooks-1.5.0.dist-info/metadata.json
django_rest_hooks-1.5.0.dist-info/top_level.txt
rest_hooks/__init__.py
rest_hooks/admin.py
rest_hooks/client.py
rest_hooks/models.py
rest_hooks/signals.py
rest_hooks/tasks.py
rest_hooks/tests.py
rest_hooks/utils.py
rest_hooks/migrations/0001_initial.py
rest_hooks/migrations/__init__.py
rest_hooks/south_migrations/0001_initial.py
rest_hooks/south_migrations/__init__.py
