Metadata-Version: 2.0
Name: django-rest-hooks
Version: 1.5.0
Summary: A powerful mechanism for sending real time API notifications via a new subscription model.
Home-page: http://github.com/zapier/django-rest-hooks
Author: Bryan Helmig
Author-email: bryan@zapier.com
License: UNKNOWN
Platform: UNKNOWN
Classifier: Development Status :: 5 - Production/Stable
Classifier: Environment :: Web Environment
Classifier: Framework :: Django
Classifier: Intended Audience :: Developers
Classifier: License :: OSI Approved :: BSD License
Classifier: Operating System :: OS Independent
Classifier: Programming Language :: Python
Classifier: Programming Language :: Python :: 2
Classifier: Programming Language :: Python :: 3
Classifier: Topic :: Utilities
Requires-Dist: Django (>=1.4)
Requires-Dist: requests
